{
    "id": 1, 
    "Description": "For farm models and modbus plc address mapping", 
    "Pump":
    [
        {
            "id": 1, 
            "address":
            {
                "modbus_id": 1, 
                "status":{
                    "tag": "FEEDBACK_PUMP_ON",
                    "position": 0, 
                    "type": "boolean"
                }, 
                "control":{
                    "tag": "CTRL_PUMP_ON", 
                    "position": 0, 
                    "type": "boolean"
                },
                "control_mode":
                {
                    "tag": "CTRL_PUMP_MODE", 
                    "position": 0, 
                    "type":"integer" 
                },
                "control_rpm":
                {
                    "tag": "CTRL_PUMP_RPM_SETPOINT",
                    "position": 0, 
                    "type": "integer"
                },
                "control_flowrate":
                {
                    "tag": "CTRL_PUMP_FLOWRATE_SETPOINT",
                    "position": 0, 
                    "type": "integer"
                }
            }
        }
    ], 
    "Light":
    [
        {
            "id": 1, 
            "address":{
                "modbus_id": 1, 
                "status": {
                    "tag": "FEEDBACK_LED",
                    "position": 0, 
                    "type": "boolean"
                },
                "control":
                {
                    "tag": "CTRL_LIGHT_ON",
                    "position": 0, 
                    "type": "boolean"
                },
                "intensity": 
                {
                    "tag": "FEEDBACK_LED_INTENSITY", 
                    "position": 0, 
                    "type": "integer"
                },
                "control_intensity":
                {
                    "tag": "CTRL_LIGHT_INTENSITY", 
                    "position": 0, 
                    "type": "integer"
                }
            }

        }
    ],
    "valve":[
        {
            "id": 1,
            "address":{
                "modbus_id": 1, 
                "control":
                {
                    "tag": "CTRL_PV_ON",
                    "position": 0, 
                    "type": "boolean"
                },
                "feedback_rpm": 
                {
                    "tag": "FEEDBACK_VALVE_SETTING", 
                    "position": 0, 
                    "type": "integer"
                },
                "control_rpm":
                {
                    "tag": "CTRL_PV_VALUE", 
                    "position": 0, 
                    "type": "integer"
                }
            }

        }

    ],
    "shelf":[
        {
            "id": 1,
            "address":{
                "modbus_id": 1, 
                "apply_update": 
                {
                    "tag": "CTRL_APPLY_UPDATE", 
                    "position": 0, 
                    "type": "sysbool"
                },
                "section_mode":
                {
                    "tag": "CTRL_SECTION_MODE", 
                    "position": 0, 
                    "type": "integer"
                }
            }
        }

    ],
    "fan":[]
}